[
    {
        "B_id":"Bid:123",
        "B":{
            "event":"B_event"
        },
        "title":"【1】创建对象",
        "subTitle":"初始化，继承，函数调用等操作",
        "event":"event",
        "sub":{
            "title":"【1-1】创建对象",
            "subTitle":"初始化，继承，函数调用等操作",
            "event":"event"
        }
    },
    {
        "title":"【2】对象、模型转换",
        "subTitle":"json和数组、字典、对象互转",
        "event":"event2"
    },
    {
        "title":"【3】自动布局",
        "subTitle":"SnapKit框架使用尝试",
        "event":"event3"
    },
    {
        "title":"【4】网络请求",
        "subTitle":"Alamofire框架使用尝试",
        "event":"event4"
    }
]
